CHANGELOG.txt
LICENCE.txt
MANIFEST.in
README.txt
setup.py
cbsi/__init__.py
cbsi.egg-info/PKG-INFO
cbsi.egg-info/SOURCES.txt
cbsi.egg-info/dependency_links.txt
cbsi.egg-info/requires.txt
cbsi.egg-info/top_level.txt