Metadata-Version: 2.1
Name: cbsi
Version: 0.0.3
Summary: Class based sensor independent Library
Home-page: https://github.com/abhinav-alangadan/CBSI
Author: Abhinav A
Author-email: abhinava.iirs.isro@gmail.com
License: MIT
Keywords: cbsi,ndvi,ndsi
Classifier: Development Status :: 5 - Production/Stable
Classifier: Intended Audience :: Education
Classifier: Operating System :: Microsoft :: Windows :: Windows 10
Classifier: License :: OSI Approved :: MIT License
Classifier: Programming Language :: Python :: 3
License-File: LICENCE.txt
